setup.py
nakuru/__init__.py
nakuru/application.py
nakuru/logger.py
nakuru/misc.py
nakuru/network.py
nakuru/protocol.py
nakuru/entities/__init__.py
nakuru/entities/components.py
nakuru/entities/device.py
nakuru/entities/file.py
nakuru/entities/friend.py
nakuru/entities/group.py
nakuru/entities/guild.py
nakuru/entities/others.py
nakuru/event/__init__.py
nakuru/event/builtins.py
nakuru/event/enums.py
nakuru/event/models.py
nakuru/examples/forward_message.py
nakuru/examples/src/forward_message.py
nakuru_project_idk-0.0.2.1.dist-info/METADATA
nakuru_project_idk-0.0.2.1.dist-info/WHEEL
nakuru_project_idk-0.0.2.1.dist-info/licenses/LICENSE
nakuru_project_idk-0.0.2.1.dist-info/RECORD
