Metadata-Version: 2.1
Name: nakuru-project-idk
Version: 0.0.2.1
Summary: 一款为 go-cqhttp 的正向 WebSocket 设计的 Python SDK，支持纯 CQ 码与消息链的转换处理
Project-URL: Homepage, https://github.com/idoknow/nakuru-project-idk
Project-URL: Bug Tracker, https://github.com/idoknow/nakuru-project-idk/issues
Author-email: Lxns-Network <joinchang1206@gmail.com>, RockChinQ <junyan_qin@qq.com>
License-File: LICENSE
Classifier: License :: OSI Approved :: MIT License
Classifier: Operating System :: OS Independent
Classifier: Programming Language :: Python :: 3
Requires-Python: >=3.7
Requires-Dist: aiohttp
Requires-Dist: async-lru
Requires-Dist: logbook
Requires-Dist: pydantic
